nimbella/__init__.py
nimbella/nimbella.py
nimbella/redisqlite.py
nimbella/storage/__init__.py
nimbella/storage/plugin_manager.py
nimbella/storage/plugins/__init__.py
nimbella/storage/plugins/abstract_storage_plugin.py
nimbella/storage/plugins/aws_storage_plugin.py
nimbella/storage/plugins/gcs_storage_plugin.py
test/__init__.py
test/test_aws_storage_plugin.py
test/test_gcs_storage_plugin.py
test/test_plugin_manager.py
test/test_redisqlite.py
nimbella-2.1.1.dist-info/LICENSE
nimbella-2.1.1.dist-info/METADATA
nimbella-2.1.1.dist-info/WHEEL
nimbella-2.1.1.dist-info/top_level.txt
nimbella-2.1.1.dist-info/zip-safe
nimbella-2.1.1.dist-info/RECORD
