Metadata-Version: 2.1
Name: nimbella
Version: 2.1.1
Summary: A python package to interact with Nimbella cloud services.
Home-page: https://github.com/nimbella/nimbella-sdk-python
Author: Nimbella Corporation
Author-email: info@nimbella.com
License: Apache-2.0
Platform: UNKNOWN
Classifier: Operating System :: OS Independent
Classifier: Programming Language :: Python
Classifier: License :: OSI Approved :: Apache Software License
License-File: LICENSE
Requires-Dist: google-cloud-storage (==1.35.1)
Requires-Dist: redis (==3.4.1)
Requires-Dist: boto3 (==1.17.5)
